Metadata-Version: 2.1
Name: unsafefunc
Version: 0.4
Summary: Better not use on main pc. For education purposes only!
Author: TheDanDev
